[
  {
    "id": "EDU-01",
    "tag": "在读",
    "degree": "信息管理硕士",
    "school": "华盛顿大学，西雅图",
    "date": "2024年9月 — 2026年6月（预计）",
    "gpa": "3.99 / 4.00",
    "logo": "uw.png",
    "honors": null,
    "subtitle": null,
    "courses": [],
    "tags": ["状态：在读", "方向：数据科学", "方向：网络安全"]
  },
  {
    "id": "EDU-02",
    "tag": "研究生",
    "degree": "计算机科学硕士",
    "school": "伊利诺伊大学厄巴纳-香槟分校",
    "date": "2019年8月 — 2024年5月",
    "gpa": "4.00 / 4.00",
    "logo": "uiuc.png",
    "honors": null,
    "subtitle": null,
    "courses": [
      "分布式系统",
      "高级分布式系统",
      "应用并行编程",
      "机器学习与数据库系统",
      "计算机系统组织",
      "云网络",
      "生成式 AI 辅助软件质量保证"
    ],
    "tags": ["方向：系统", "RA：Tarek Abdelzaher 教授"]
  },
  {
    "id": "EDU-03",
    "tag": "本科",
    "degree": "计算机科学学士",
    "school": "伊利诺伊大学厄巴纳-香槟分校",
    "date": "2019年8月 — 2024年5月",
    "gpa": "4.00 / 4.00",
    "logo": "uiuc.png",
    "honors": null,
    "subtitle": null,
    "courses": [
      "数据库系统",
      "Web 开发",
      "系统编程",
      "人工智能",
      "计算机体系结构",
      "算法与计算模型",
      "数据结构",
      "应用机器学习",
      "交互式计算机图形学"
    ],
    "tags": ["最高荣誉毕业", "院长名单：2019秋–2022秋"]
  }
]
